<linki><link><typ>zespoły</typ><nazwa>Jack Band</nazwa><adres>http://www.jackandband.com.pl</adres></link><link><typ>zespoły</typ><nazwa>Nie Ma Sprawy - tel. 33 870 14 92</nazwa><adres>http://niemasprawy.pl</adres></link><link><typ>zespoły</typ><nazwa>Dj-Wodzirej-Karolo</nazwa><adres>http://djiwodzirej.pl</adres></link><link><typ>zespoły</typ><nazwa>Ameryka</nazwa><adres>https://www.facebook.com/Zespół-Ameryka-1658667817762664/?modal=media_composer</adres></link><link><typ>zespoły</typ><nazwa>Kolektiv Band</nazwa><adres>http://www.kolektivband.pl</adres></link><link><typ>zespoły</typ><nazwa>DJ-Wodzirej Mariusz Chuchmacz - tel. 513 290 290</nazwa><adres>brak</adres></link><link><typ>zespoły</typ><nazwa>Różowa Pantera - tel. 606 309 281</nazwa><adres>http://www.rozowapantera.pl</adres></link><link><typ>zespoły</typ><nazwa>Reda</nazwa><adres>http://www.zespolreda.pl</adres></link><link><typ>zespoły</typ><nazwa>Talizman - www.talizman.net.pl</nazwa><adres>http://www.talizman.net.pl</adres></link><link><typ>zespoły</typ><nazwa>Rajda-Band</nazwa><adres>http://rajda-band.pl</adres></link><link><typ>zespoły</typ><nazwa>Vega - tel. 505 038 880</nazwa><adres>http://www.vega-vega.pl</adres></link><link><typ>zespoły</typ><nazwa>Edison - tel. 602 423 875</nazwa><adres>www.facebook.com/zespoledison</adres></link><link><typ>zespoły</typ><nazwa>Aramis</nazwa><adres>http://www.aramis.andrychow.pl</adres></link><link><typ>zespoły</typ><nazwa>Figaro - tel. 723 348 973</nazwa><adres>brak</adres></link><link><typ>zespoły</typ><nazwa>Desperado - tel. 602 404 149</nazwa><adres>brak</adres></link><link><typ>zespoły</typ><nazwa>Remix Band - tel. 884 217 303</nazwa><adres>http://www.theremixband.pl</adres></link><link><typ>zespoły</typ><nazwa>Kapela Wielkopolska - Kotkowiacy</nazwa><adres>http://www.kotkowiacy.pl</adres></link><link><typ>foto-video</typ><nazwa>PyszStudio - Ewa i Piotr Pysz</nazwa><adres>http://www.pyszstudio.pl</adres></link><link><typ>foto-video</typ><nazwa>Foto-Video Centrum bracia Olajossy</nazwa><adres>http://www.fotograf-andrychow.pl</adres></link><link><typ>foto-video</typ><nazwa>Tadeusz Sztuka</nazwa><adres>http://www.fotovideosztuka.bo.pl</adres></link><link><typ>foto-video</typ><nazwa>Łukasz Sztuka</nazwa><adres>http://www.sztukastudio.pl</adres></link><link><typ>foto-video</typ><nazwa>Bieniek Władysław Studio Nagrań Filmowych - tel. 33 873 85 44</nazwa><adres>brak</adres></link><link><typ>foto-video</typ><nazwa>Studio Foto-Wideo-Zygmunt Piwowarczyk - tel. 507 179 213</nazwa><adres>brak</adres></link><link><typ>foto-video</typ><nazwa>Admont2 - tel. 668 303 163</nazwa><adres>http://www.admont.wix.com/admont</adres></link><link><typ>foto-video</typ><nazwa>ART-FOTO-VIDEO - Marcin Bukała</nazwa><adres>http://www.art-foto-video.pl</adres></link><link><typ>foto-video</typ><nazwa>BETA</nazwa><adres>http://www.videobeta.com</adres></link><link><typ>foto-video</typ><nazwa>Foto-Video Sepia - tel. 500 738 352, 33 870 53 83</nazwa><adres>brak</adres></link><link><typ>foto-video</typ><nazwa>Ireneusz Snopkiewicz</nazwa><adres>http://www.studiodvd-film.pl</adres></link><link><typ>foto-video</typ><nazwa>Adam Mleczko - tel. 604-334-447</nazwa><adres>brak</adres></link><link><typ>foto-video</typ><nazwa>FOTO-MIX</nazwa><adres>http://www.foto-mix.com.pl</adres></link><link><typ>foto-video</typ><nazwa>Paweł Kostka "PSTRYK" - tel. 604 113 474</nazwa><adres>brak</adres></link><link><typ>foto-video</typ><nazwa>Tomek Niesyt - tel. 691 694 930</nazwa><adres>http://www.pracownia-fotografii.pl</adres></link><link><typ>foto-video</typ><nazwa>Mariusz Markowski - tel. 661 070 491 </nazwa><adres>brak</adres></link><link><typ>foto-video</typ><nazwa>Studio 2M</nazwa><adres>http://www.studio2m.com.pl</adres></link><link><typ>foto-video</typ><nazwa>Mariusz Muzyk</nazwa><adres>http://www.marmuz.xon.pl</adres></link><link><typ>foto-video</typ><nazwa>Zbyszek Lata</nazwa><adres>http://www.portfolioslubne.pl</adres></link><link><typ>foto-video</typ><nazwa>Mariusz Markowski - tel. 0 661 070 491</nazwa><adres>brak</adres></link><link><typ>foto-video</typ><nazwa>Mariusz Połówczuk</nazwa><adres>http://www.polowczuk-foto.pl/justynawojtek</adres></link><link><typ>foto-video</typ><nazwa>Łukasz Czyż</nazwa><adres>http://www.digitalsystem.com.pl</adres></link><link><typ>foto-video</typ><nazwa>Delfin Studio</nazwa><adres>http://www.studiodelfin.com</adres></link><link><typ>foto-video</typ><nazwa>Centrum Fotograficzne"OBRAZEK" Arkadiusz Tumidajski - tel. 508 560 103</nazwa><adres>https://www.facebook.com/fotoobrazek</adres></link><link><typ>foto-video</typ><nazwa>Łukasz Błaszków - lukasz.blaszkow@gmail.com</nazwa><adres>brak</adres></link><link><typ>foto-video</typ><nazwa>OES Records</nazwa><adres>http://www.oesrecords.pl</adres></link><link><typ>foto-video</typ><nazwa>Fotografia Ślubna Krzysztof Adamik - tel. 502 782 256</nazwa><adres>brak</adres></link><link><typ>foto-video</typ><nazwa>Studio Video Royal - tel. 502 353 870</nazwa><adres>brak</adres></link><link><typ>foto-video</typ><nazwa>RS VISION Studio Fotografii Artystycznej</nazwa><adres>http://www.rsvision.pl</adres></link><link><typ>foto-video</typ><nazwa>Daniel Gromala</nazwa><adres>http://www.fotogromala.pl</adres></link><link><typ>foto-video</typ><nazwa>Anna i Jacek Bieniek</nazwa><adres>http://www.magiaobrazu.com</adres></link><link><typ>foto-video</typ><nazwa>Grzesiek Gawenda- GGFotograf</nazwa><adres>http://mgfotograficy.blogspot.com/</adres></link><link><typ>lokale</typ><nazwa>Jurek Catering-Serwis</nazwa><adres>http://www.jurek-catering.pl</adres></link><link><typ>lokale</typ><nazwa>Przystań u Lipy - tel. 18 267 43 95</nazwa><adres>http://www.ulipy.com.pl</adres></link><link><typ>lokale</typ><nazwa>Zielona Skarpa</nazwa><adres>http://www.zielonaskarpa.andrychow.pl</adres></link><link><typ>lokale</typ><nazwa>Pasja</nazwa><adres>http://www.weselepasja.pl</adres></link><link><typ>lokale</typ><nazwa>Łysoń Park-Hotel</nazwa><adres>http:// www.parkhotellyson.pl</adres></link><link><typ>lokale</typ><nazwa>Karczma Młynówka</nazwa><adres>http://www.karczmamlynowka.eu</adres></link><link><typ>lokale</typ><nazwa>Karpik</nazwa><adres>http://www.karpik.pl</adres></link><link><typ>lokale</typ><nazwa>Karczma Kocierz</nazwa><adres>http://www.kocierz.pl</adres></link><link><typ>lokale</typ><nazwa>Restauracja "Adria" - te. 33 875 29 32</nazwa><adres>brak</adres></link><link><typ>lokale</typ><nazwa>Restauracja "Pinocy"</nazwa><adres>http://www.pinocy.com.pl</adres></link><link><typ>lokale</typ><nazwa>Sala bankietowa "ATENA" w Sosnowcu - tel. 32 293 81 83</nazwa><adres>brak</adres></link><link><typ>lokale</typ><nazwa>Dom Weselny "Polonez"</nazwa><adres>http://www.polonez.net.pl</adres></link><link><typ>lokale</typ><nazwa>Restauracja Nova Plus - Wadowice</nazwa><adres>http://www.novaplus.pl</adres></link><link><typ>lokale</typ><nazwa>Restauracja Magik - Andrychów</nazwa><adres>http://magik.andrychow.pl</adres></link><link><typ>lokale</typ><nazwa>Klub Kręgielnia Wadowice</nazwa><adres>http://klubkregielnia.pl</adres></link><link><typ>lokale</typ><nazwa>Czarny Groń</nazwa><adres>http://www.czarnygron.pl/</adres></link><link><typ>inne</typ><nazwa>Agencja Promocyjno-Koncertowa IDEALY SP. Z O.O - Mariusz Kapuśniak - tel:501-731-482</nazwa></link><link><typ>inne</typ><nazwa>Rafał(twórca strony) - kuchasz1@o2.pl</nazwa><adres>brak</adres></link><link><typ>inne</typ><nazwa>Bus do wynajęcia "Ekocars" - tel: 530 547 873, 576 797 145</nazwa><adres>brak</adres></link><link><typ>inne</typ><nazwa>Akcesoria na imprezy okolicznościowe - ESK Elstek Krystian Ruła</nazwa><adres>http://www.elstek.pl</adres></link><link><typ>inne</typ><nazwa>Nauka gry na instrumentach - Wojciech i  Piotrek Zięba - tel. 604 671 973, 600 632 798</nazwa><adres>brak</adres></link><link><typ>inne</typ><nazwa>Mechanika pojazdów samochodowych, lakiernictwo, blacharka, instalacje gazowe - Zię-Mot - tel. 606 517 661</nazwa><adres>brak</adres></link><link><typ>inne</typ><nazwa>Dekoracja i organizacja imprez-Studio ABI</nazwa><adres>http://studioimprezabi.pl</adres></link><link><typ>inne</typ><nazwa>Mojito - Tomasz Dybała - alkohole</nazwa><adres>http://www.mojito.info.pl</adres></link><link><typ>inne</typ><nazwa>Jubiler - Paweł Kościelnik - tel. 33 488 64 38</nazwa><adres>http://netrona.pl/system/oferta?of=197</adres></link><link><typ>inne</typ><nazwa>Sklep "Okazja"-artykuły na każdą okoliczność</nazwa><adres>http://www.sklep-okazja.pl/</adres></link><link><typ>inne</typ><nazwa>Centrum mody "Asmen"</nazwa><adres>http://www.asmen.pl</adres></link><link><typ>inne</typ><nazwa>Dekoracje i rękodzieło "Bellissima"</nazwa><adres>http://www.bellissima-dekoracje.pl</adres></link><link><typ>inne</typ><nazwa>Cukiernia "Merta"</nazwa><adres>http://cukierniamerta.pl</adres></link><link><typ>inne</typ><nazwa>Zaproszenia ślubne "Perfect Story"</nazwa><adres>http://zaproszenia-ps.com.pl</adres></link><link><typ>inne</typ><nazwa>Samochody do ślubu</nazwa><adres>http://www.macmar.net.pl</adres></link><link><typ>inne</typ><nazwa>Firma Budowlana - Proj-Bud - tel. 888 871 017</nazwa><adres>brak</adres></link><link><typ>inne</typ><nazwa>Naprawa instrumentów dętych - Roman i Michał Zięba</nazwa><adres>http://www.ziebamusic.pl</adres></link><link><typ>inne</typ><nazwa>"Świetne noclegi nad morzem" Adam Muzyk - tel. 512 678 459</nazwa><adres>brak</adres></link><link><typ>inne</typ><nazwa>Obsługa kelnerska, kierowca, sprzątanie - tel. 884 210 213, 600 614 102</nazwa><adres>brak</adres></link></linki>
